wgmesh/__init__.py
wgmesh/config.py
wgmesh/core.py
wgmesh/deploy.py
wgmesh/endpointdb.py
wgmesh/host.py
wgmesh/hostinit.py
wgmesh/pub.py
wgmesh/pubhost.py
wgmesh/route53.py
wgmesh/site.py
wgmesh/templates.py
wgmesh/version.py
wgmesh-1.0.2.dist-info/LICENSE
wgmesh-1.0.2.dist-info/METADATA
wgmesh-1.0.2.dist-info/WHEEL
wgmesh-1.0.2.dist-info/entry_points.txt
wgmesh-1.0.2.dist-info/top_level.txt
wgmesh-1.0.2.dist-info/RECORD
