Metadata-Version: 2.1
Name: wgmesh
Version: 1.0.2
Summary: Wireguard Mesh Maker
Home-page: https://github.com/joshland/wgmesh
Author: Joshua M. Schmidlkofer
Author-email: joshua.schmidlkofer@erickson.is
License: UNKNOWN
Keywords: wireguard frr
Platform: UNKNOWN
Classifier: Environment :: Console
Classifier: Intended Audience :: Information Technology
Classifier: License :: OSI Approved :: MIT License
Classifier: Programming Language :: Python :: 3
Classifier: Programming Language :: Python :: 3.5
Classifier: Programming Language :: Python :: 3.6
Classifier: Programming Language :: Python :: 3.7
Classifier: Programming Language :: Python :: 3.8
Classifier: Programming Language :: Python :: 3.9
Classifier: Operating System :: POSIX :: Linux
Classifier: Topic :: Internet
Classifier: Topic :: System :: Networking
Classifier: Development Status :: 4 - Beta
Classifier: Natural Language :: English
Requires-Dist: wheel
Requires-Dist: attrs
Requires-Dist: click
Requires-Dist: dnspython
Requires-Dist: ifaddr
Requires-Dist: loguru
Requires-Dist: natsort
Requires-Dist: netaddr
Requires-Dist: pynacl
Requires-Dist: route53
Requires-Dist: ruamel.yaml
Requires-Dist: six
Requires-Dist: jinja2
